pixelpin_auth_django
