Metadata-Version: 1.1
Name: pixelpin-auth-django
Version: 1.0.1
Summary: Python PixelPin Authentication, Django integration.
Home-page: https://github.com/python-social-auth/social-app-django
Author: ['Matias Aguirre', 'Callum Brankin']
Author-email: callum@pixelpin.co.uk
License: BSD
Keywords: django,social auth,pixelpin auth
Platform: UNKNOWN
Classifier: Development Status :: 4 - Beta
Classifier: Topic :: Internet
Classifier: License :: OSI Approved :: BSD License
Classifier: Intended Audience :: Developers
Classifier: Environment :: Web Environment
Classifier: Programming Language :: Python
Classifier: Programming Language :: Python :: 2.7
Classifier: Programming Language :: Python :: 3
